csv_detective/__init__.py
csv_detective/cli.py
csv_detective/detection/__init__.py
csv_detective/detection/columns.py
csv_detective/detection/encoding.py
csv_detective/detection/engine.py
csv_detective/detection/formats.py
csv_detective/detection/headers.py
csv_detective/detection/rows.py
csv_detective/detection/separator.py
csv_detective/detection/variables.py
csv_detective/explore_csv.py
csv_detective/format.py
csv_detective/formats/__init__.py
csv_detective/formats/adresse.py
csv_detective/formats/binary.py
csv_detective/formats/booleen.py
csv_detective/formats/code_commune_insee.py
csv_detective/formats/code_csp_insee.py
csv_detective/formats/code_departement.py
csv_detective/formats/code_fantoir.py
csv_detective/formats/code_import.py
csv_detective/formats/code_postal.py
csv_detective/formats/code_region.py
csv_detective/formats/code_rna.py
csv_detective/formats/code_waldec.py
csv_detective/formats/commune.py
csv_detective/formats/csp_insee.py
csv_detective/formats/data/csp_insee.txt
csv_detective/formats/data/insee_ape700.txt
csv_detective/formats/data/iso_country_code_alpha2.txt
csv_detective/formats/data/iso_country_code_alpha3.txt
csv_detective/formats/data/iso_country_code_numeric.txt
csv_detective/formats/date.py
csv_detective/formats/date_fr.py
csv_detective/formats/datetime_aware.py
csv_detective/formats/datetime_naive.py
csv_detective/formats/datetime_rfc822.py
csv_detective/formats/departement.py
csv_detective/formats/email.py
csv_detective/formats/float.py
csv_detective/formats/geojson.py
csv_detective/formats/insee_ape700.py
csv_detective/formats/insee_canton.py
csv_detective/formats/int.py
csv_detective/formats/iso_country_code_alpha2.py
csv_detective/formats/iso_country_code_alpha3.py
csv_detective/formats/iso_country_code_numeric.py
csv_detective/formats/jour_de_la_semaine.py
csv_detective/formats/json.py
csv_detective/formats/latitude_l93.py
csv_detective/formats/latitude_wgs.py
csv_detective/formats/latitude_wgs_fr_metropole.py
csv_detective-0.10.2549.dist-info/WHEEL
csv_detective-0.10.2549.dist-info/entry_points.txt
csv_detective-0.10.2549.dist-info/METADATA
csv_detective-0.10.2549.dist-info/RECORD
