Metadata-Version: 2.3
Name: csv-detective
Version: 0.10.2549
Summary: Detect tabular files column content
Keywords: CSV,data processing,encoding,guess,parser,tabular
Author: data.gouv.fr
Author-email: data.gouv.fr <opendatateam@data.gouv.fr>
License: MIT
Requires-Dist: dateparser>=1.2.0,<2
Requires-Dist: faust-cchardet==2.1.19
Requires-Dist: pandas>=2.2.0,<3
Requires-Dist: python-dateutil>=2.8.2,<3
Requires-Dist: unidecode>=1.3.6,<2
Requires-Dist: openpyxl>=3.1.5
Requires-Dist: xlrd>=2.0.1
Requires-Dist: odfpy>=1.4.1
Requires-Dist: requests>=2.32.3,<3
Requires-Dist: python-magic>=0.4.27
Requires-Dist: frformat==0.4.0
Requires-Dist: faker>=33.0.0
Requires-Dist: rstr>=3.2.2
Requires-Dist: more-itertools>=10.8.0
Requires-Dist: pytest>=8.3.0 ; extra == 'dev'
Requires-Dist: responses>=0.25.0 ; extra == 'dev'
Requires-Dist: ruff>=0.9.3 ; extra == 'dev'
Requires-Python: >=3.10, <3.15
Project-URL: Source, https://github.com/datagouv/csv_detective
Provides-Extra: dev
